dyad_cli/__init__.py
dyad_cli/py.typed
dyad_cli/user_data_dir_utils.py
dyad_cli/version.py
dyad-0.2.3.dist-info/METADATA
dyad-0.2.3.dist-info/WHEEL
dyad-0.2.3.dist-info/entry_points.txt
dyad-0.2.3.dist-info/RECORD
