Metadata-Version: 2.4
Name: dyad
Version: 0.2.3
Summary: Add your description here
Author-email: Will Chen <willchen90@gmail.com>
Requires-Python: >=3.8
Requires-Dist: uv>=0.5.0
